pamalia/__init__.py
pamalia-0.0.2.dist-info/METADATA
pamalia-0.0.2.dist-info/RECORD
pamalia-0.0.2.dist-info/WHEEL
pamalia-0.0.2.dist-info/top_level.txt
