Metadata-Version: 2.1
Name: pamalia
Version: 0.0.2
Summary: UNKNOWN
Home-page: https://github.com/louisabraham/pamalia
Author: Louis Abraham
Author-email: louis.abraham@yahoo.fr
License: MIT
Platform: UNKNOWN
Requires-Python: >=3.6
Requires-Dist: scikit-learn
